drb/topics/sentinel3/__init__.py
drb/topics/sentinel3/_version.py
drb/topics/sentinel3/cortex.yml
drb/topics/sentinel3/Auxiliary/__init__.py
drb/topics/sentinel3/Auxiliary/cortex.yml
drb/topics/sentinel3/DORIS/__init__.py
drb/topics/sentinel3/DORIS/level0/__init__.py
drb/topics/sentinel3/DORIS/level0/cortex.yml
drb/topics/sentinel3/GNSS/__init__.py
drb/topics/sentinel3/GNSS/level0/__init__.py
drb/topics/sentinel3/GNSS/level0/cortex.yml
drb/topics/sentinel3/MRW/__init__.py
drb/topics/sentinel3/MRW/level0/__init__.py
drb/topics/sentinel3/MRW/level0/cortex.yml
drb/topics/sentinel3/MRW/level1/__init__.py
drb/topics/sentinel3/MRW/level1/cortex.yml
drb/topics/sentinel3/OLCI/__init__.py
drb/topics/sentinel3/OLCI/cortex.yml
drb/topics/sentinel3/OLCI/level0/__init__.py
drb/topics/sentinel3/OLCI/level0/cortex.yml
drb/topics/sentinel3/OLCI/level1/__init__.py
drb/topics/sentinel3/OLCI/level1/cortex.yml
drb/topics/sentinel3/OLCI/level2/__init__.py
drb/topics/sentinel3/OLCI/level2/cortex.yml
drb/topics/sentinel3/SLSTR/__init__.py
drb/topics/sentinel3/SLSTR/cortex.yml
drb/topics/sentinel3/SLSTR/level0/__init__.py
drb/topics/sentinel3/SLSTR/level0/cortex.yml
drb/topics/sentinel3/SLSTR/level1/__init__.py
drb/topics/sentinel3/SLSTR/level1/cortex.yml
drb/topics/sentinel3/SLSTR/level2/__init__.py
drb/topics/sentinel3/SLSTR/level2/cortex.yml
drb/topics/sentinel3/SRAL/__init__.py
drb/topics/sentinel3/SRAL/cortex.yml
drb/topics/sentinel3/SRAL/level0/__init__.py
drb/topics/sentinel3/SRAL/level0/cortex.yml
drb/topics/sentinel3/SRAL/level1/__init__.py
drb/topics/sentinel3/SRAL/level1/cortex.yml
drb/topics/sentinel3/SRAL/level2/__init__.py
drb/topics/sentinel3/SRAL/level2/cortex.yml
drb/topics/sentinel3/SYN/__init__.py
drb/topics/sentinel3/SYN/cortex.yml
drb/topics/sentinel3/SYN/level1/__init__.py
drb/topics/sentinel3/SYN/level1/cortex.yml
drb/topics/sentinel3/SYN/level2/__init__.py
drb/topics/sentinel3/SYN/level2/cortex.yml
drb/topics/sentinel3/Telemetry/__init__.py
drb_topic_sentinel3-1.2.0.dist-info/LICENCE.txt
drb_topic_sentinel3-1.2.0.dist-info/METADATA
drb_topic_sentinel3-1.2.0.dist-info/WHEEL
drb_topic_sentinel3-1.2.0.dist-info/entry_points.txt
drb_topic_sentinel3-1.2.0.dist-info/top_level.txt
drb_topic_sentinel3-1.2.0.dist-info/RECORD
